.svnignore
CONTRIBUTORS.txt
README.txt
setup.cfg
setup.py
docs/HISTORY.txt
slc/__init__.py
slc.autotranslate.egg-info/PKG-INFO
slc.autotranslate.egg-info/SOURCES.txt
slc.autotranslate.egg-info/dependency_links.txt
slc.autotranslate.egg-info/entry_points.txt
slc.autotranslate.egg-info/namespace_packages.txt
slc.autotranslate.egg-info/not-zip-safe
slc.autotranslate.egg-info/requires.txt
slc.autotranslate.egg-info/top_level.txt
slc/autotranslate/README.txt
slc/autotranslate/__init__.py
slc/autotranslate/config.py
slc/autotranslate/configure.zcml
slc/autotranslate/events.py
slc/autotranslate/flashupload_success.pt
slc/autotranslate/interfaces.py
slc/autotranslate/overrides.zcml
slc/autotranslate/schemaextender.py
slc/autotranslate/setuphandlers.py
slc/autotranslate/tests.py
slc/autotranslate/utils.py
slc/autotranslate/profiles/default/metadata.xml
slc/autotranslate/profiles/default/slc_autotranslate_marker.txt
slc/autotranslate/tests/doctests.txt
slc/autotranslate/tests/files/cs_file.txt
slc/autotranslate/tests/files/de_file.txt
slc/autotranslate/tests/files/en_file.txt
slc/autotranslate/tests/files/file.txt
slc/autotranslate/tests/files/file_es.txt
slc/autotranslate/tests/files/fr_file.txt