Metadata-Version: 1.0
Name: slc.autotranslate
Version: 1.5.4
Summary: Automatically translate files uploaded by PloneFlashUpload
Home-page: http://plone.org/products/slc.autotranslate
Author: JC Brand
Author-email: brand@syslab.com
License: GPL
Keywords: plone zope PloneFlashUpload LinguagePlone translate pdf upload slc syslab
Platform: UNKNOWN
Classifier: Programming Language :: Python
Classifier: Topic :: Software Development :: Libraries :: Python Modules
